README.md
setup.cfg
setup.py
s3sh/__init__.py
s3sh/repl.py
s3sh.egg-info/PKG-INFO
s3sh.egg-info/SOURCES.txt
s3sh.egg-info/dependency_links.txt
s3sh.egg-info/not-zip-safe
s3sh.egg-info/requires.txt
s3sh.egg-info/top_level.txt
s3sh/cli/s3sh
s3sh/cli/s3sh.bat
s3sh/cli/__init__.py