Metadata-Version: 1.0
Name: s3sh
Version: 0.1.6
Summary: A repl for s3
Home-page: https://github.com/WRRB/s3sh
Author: Wim Berchmans
Author-email: wimberchmans@gmail.com
License: UNKNOWN
Platform: UNKNOWN
